{
	"forge_marker": 1,
	"defaults": {
		"model": "forge:multi-layer",
		"transform": "forge:default-block"
	},
	"variants": {
		"normal": [{
			"custom": {
				"base": "tinymobfarm:emerald_generator#base",
				"Solid": "tinymobfarm:emerald_generator#base",
				"Cutout": "tinymobfarm:emerald_generator#glass"
			}
		}],
		"base": [{
			"model": "tinymobfarm:emerald_generator"
		}],
		"glass": [{
			"model": "tinymobfarm:glass_panel"
		}],
		"inventory": [{
			"custom": {
				"base": "tinymobfarm:emerald_generator#base",
				"Solid": "tinymobfarm:emerald_generator#base",
				"Cutout": "tinymobfarm:emerald_generator#glass"
			}
		}]
	}
}